{
  "id": "17",
  "subject": "執行驗證測試並提交代碼",
  "description": "**What**: 運行測試確保修改沒有破壞現有功能，然後提交所有更改\n\n**Where**: 專案根目錄\n\n**How**: \n1. 執行 Python 測試：\n```bash\ncd python-env && python -m pytest tests/ -v\n```\n\n2. 執行手動驗證腳本：\n```bash\npython -c \"\nfrom joker_env.reward import *\nprint('ante_progress(1,2):', ante_progress_reward(1, 2))\nprint('blind_clear(Small):', blind_clear_reward(2, 0, 1))\nprint('skip(Small,avg):', skip_blind_reward(0, 1, None))\nprint('skip(Small,Neg):', skip_blind_reward(0, 1, TAG_NEGATIVE))\n\"\n```\n\n3. 確認輸出符合預期後，提交代碼：\n```bash\ngit add -A\ngit commit -m \"feat: rebalance reward system for better ante progression (v5.0)\"\n```\n\n**Why**: 確保所有修改正確無誤後再提交。\n\n**Verify**: \n- pytest 全部通過\n- ante_progress(1,2) ≈ 0.48\n- blind_clear(Small) ≈ 0.25\n- skip(Small,Neg) ≈ 0.18（低於原本的 0.44）",
  "activeForm": "執行驗證測試並提交",
  "status": "pending",
  "blocks": [],
  "blockedBy": [
    "8",
    "9",
    "10",
    "11",
    "12",
    "13",
    "14",
    "15",
    "16"
  ]
}